{
    "type": "object",
    "properties": {
        "userId": {
            "required": true,
            "type": "string"
        },
        "type": {
            "type": "string",
            "enum": [
                "scheduled",
                "live"
            ],
            "default": "live"
        },
        "page_size": {
            "type": "integer",
            "maximum": 300,
            "default": 30
        },
        "page_number": {
            "type": "integer",
            "default": 1
        }
    }
}